animation/__init__.py
animation/animation.py
kohonen_som-0.0.1.dist-info/LICENSE
kohonen_som-0.0.1.dist-info/METADATA
kohonen_som-0.0.1.dist-info/WHEEL
kohonen_som-0.0.1.dist-info/top_level.txt
kohonen_som-0.0.1.dist-info/RECORD
