Metadata-Version: 2.1
Name: kohonen-som
Version: 0.0.1
Summary: PyTorch implementation of Kohonen's Self-Organizing Map.
Home-page: https://github.com/nicomignoni/SOM
Author: Nicola Mignoni
Author-email: nicola.mignoni@gmail.com
License: UNKNOWN
Platform: UNKNOWN
Classifier: Programming Language :: Python :: 3
Classifier: License :: OSI Approved :: MIT License
Classifier: Operating System :: OS Independent
Requires-Python: >=3.6
